odoo/addons/webservice/README.rst
odoo/addons/webservice/__init__.py
odoo/addons/webservice/__manifest__.py
odoo/addons/webservice/components/__init__.py
odoo/addons/webservice/components/base_adapter.py
odoo/addons/webservice/components/request_adapter.py
odoo/addons/webservice/i18n/webservice.pot
odoo/addons/webservice/models/__init__.py
odoo/addons/webservice/models/webservice_backend.py
odoo/addons/webservice/readme/CONTRIBUTORS.rst
odoo/addons/webservice/readme/DESCRIPTION.rst
odoo/addons/webservice/security/ir.model.access.csv
odoo/addons/webservice/static/description/icon.png
odoo/addons/webservice/static/description/index.html
odoo/addons/webservice/tests/__init__.py
odoo/addons/webservice/tests/common.py
odoo/addons/webservice/tests/test_webservice.py
odoo/addons/webservice/views/webservice_backend.xml
odoo13_addon_webservice-13.0.1.0.1.dist-info/METADATA
odoo13_addon_webservice-13.0.1.0.1.dist-info/WHEEL
odoo13_addon_webservice-13.0.1.0.1.dist-info/top_level.txt
odoo13_addon_webservice-13.0.1.0.1.dist-info/RECORD
