Metadata-Version: 2.1
Name: odoo13-addon-webservice
Version: 13.0.1.0.1
Summary: Defines webservice abstract definition to be used generally
Home-page: https://github.com/OCA/edi
Author: Creu Blanca,Odoo Community Association (OCA)
Author-email: support@odoo-community.org
License: AGPL-3
Platform: UNKNOWN
Classifier: Programming Language :: Python
Classifier: Framework :: Odoo
Classifier: License :: OSI Approved :: GNU Affero General Public License v3
Classifier: Development Status :: 3 - Alpha
Requires-Python: >=3.5
Requires-Dist: odoo13-addon-component
Requires-Dist: odoo13-addon-server-environment
Requires-Dist: odoo (<13.1dev,>=13.0a)
